odoo/addons/shopinvader_search_engine_update_product_brand_image/README.rst
odoo/addons/shopinvader_search_engine_update_product_brand_image/__init__.py
odoo/addons/shopinvader_search_engine_update_product_brand_image/__manifest__.py
odoo/addons/shopinvader_search_engine_update_product_brand_image/i18n/shopinvader_search_engine_update_product_brand_image.pot
odoo/addons/shopinvader_search_engine_update_product_brand_image/models/__init__.py
odoo/addons/shopinvader_search_engine_update_product_brand_image/models/fs_product_brand_image.py
odoo/addons/shopinvader_search_engine_update_product_brand_image/readme/CONTEXT.md
odoo/addons/shopinvader_search_engine_update_product_brand_image/readme/CONTRIBUTORS.md
odoo/addons/shopinvader_search_engine_update_product_brand_image/readme/DESCRIPTION.md
odoo/addons/shopinvader_search_engine_update_product_brand_image/static/description/icon.png
odoo/addons/shopinvader_search_engine_update_product_brand_image/static/description/index.html
odoo/addons/shopinvader_search_engine_update_product_brand_image/tests/__init__.py
odoo/addons/shopinvader_search_engine_update_product_brand_image/tests/test_update.py
odoo_addon_shopinvader_search_engine_update_product_brand_image-16.0.1.0.0.2.dist-info/METADATA
odoo_addon_shopinvader_search_engine_update_product_brand_image-16.0.1.0.0.2.dist-info/WHEEL
odoo_addon_shopinvader_search_engine_update_product_brand_image-16.0.1.0.0.2.dist-info/top_level.txt
odoo_addon_shopinvader_search_engine_update_product_brand_image-16.0.1.0.0.2.dist-info/RECORD
